{"cameraMode":{"drawMode":0,"name":"Shaded","section":"Shading Mode"},"sceneLighting":true,"audioPlay":false,"sceneViewState":{"m_AlwaysRefresh":false,"showFog":true,"showSkybox":true,"showFlares":true,"showImageEffects":true,"showParticleSystems":true,"showVisualEffectGraphs":true,"m_FxEnabled":true},"in2DMode":false,"pivot":{"x":1.3961807489395142,"y":1.0137649774551392,"z":-0.14544019103050233},"rotation":{"x":-0.0031922589987516405,"y":0.994691014289856,"z":-0.09760195016860962,"w":-0.0325370728969574},"size":1.3725436925888062,"orthographic":false}